italian_political_compass/__init__.py
italian_political_compass/core.py
italian_political_compass/data/weights.py
italian_political_compass-0.1.2.dist-info/METADATA
italian_political_compass-0.1.2.dist-info/WHEEL
italian_political_compass-0.1.2.dist-info/top_level.txt
italian_political_compass-0.1.2.dist-info/RECORD
