Metadata-Version: 2.1
Name: italian-political-compass
Version: 0.1.2
Summary: A political compass tool using AI
Home-page: https://github.com/mii-llm/propaganda
Author: financialsupport
Author-email: marvin994@gmail.com
Classifier: Programming Language :: Python :: 3
Classifier: License :: OSI Approved :: MIT License
Classifier: Operating System :: OS Independent
Requires-Python: >=3.6
Requires-Dist: torch
Requires-Dist: transformers
